{
  "properties": {
    "facing": [
      "north",
      "south",
      "west",
      "east"
    ],
    "last_interaction_book_slot": [
      "0",
      "1",
      "2",
      "3",
      "4",
      "5",
      "6"
    ],
    "slot_0_occupied": [
      "true",
      "false"
    ],
    "slot_1_occupied": [
      "true",
      "false"
    ],
    "slot_2_occupied": [
      "true",
      "false"
    ],
    "slot_3_occupied": [
      "true",
      "false"
    ],
    "slot_4_occupied": [
      "true",
      "false"
    ],
    "slot_5_occupied": [
      "true",
      "false"
    ]
  },
  "default": {
    "facing": "north",
    "last_interaction_book_slot": "0",
    "slot_0_occupied": "false",
    "slot_1_occupied": "false",
    "slot_2_occupied": "false",
    "slot_3_occupied": "false",
    "slot_4_occupied": "false",
    "slot_5_occupied": "false"
  }
}
