{
  "parent": "minecraft:adventure/craft_table",
  "criteria": {
    "obsidian": {
      "conditions": {
        "entity": [
          {
            "condition": "minecraft:entity_properties",
            "entity": "this",
            "predicate": {
              "type": "minecraft:living_block",
              "type_specific": {
                "type": "minecraft:living_block",
                "item": {
                  "items": "minecraft:obsidian"
                }
              }
            }
          }
        ]
      },
      "trigger": "minecraft:summoned_entity"
    }
  },
  "display": {
    "description": {
      "translate": "advancements.adventure.obsidian.description"
    },
    "icon": {
      "id": "minecraft:obsidian"
    },
    "title": {
      "translate": "advancements.adventure.obsidian.title"
    }
  },
  "requirements": [
    [
      "obsidian"
    ]
  ],
  "sends_telemetry_event": true
}