{
  "type": "minecraft:sequence",
  "sequence": [
    {
      "type": "minecraft:condition",
      "if_true": "minecraft:on_floor",
      "then_run": {
        "type": "minecraft:sequence",
        "sequence": [
          {
            "type": "minecraft:condition",
            "if_true": {
              "type": "minecraft:biome",
              "biome_is": "minecraft:wooded_badlands"
            },
            "then_run": {
              "type": "minecraft:condition",
              "if_true": {
                "type": "minecraft:y_above",
                "add_stone_depth": false,
                "anchor": {
                  "absolute": 97
                },
                "surface_depth_multiplier": 2
              },
              "then_run": {
                "type": "minecraft:sequence",
                "sequence": [
                  {
                    "type": "minecraft:condition",
                    "if_true": {
                      "type": "minecraft:noise_threshold",
                      "max_threshold": -0.5454,
                      "min_threshold": -0.909,
                      "noise": "minecraft:surface"
                    },
                    "then_run": {
                      "type": "minecraft:block",
                      "result_state": {
                        "Name": "minecraft:coarse_dirt"
                      }
                    }
                  },
                  {
                    "type": "minecraft:condition",
                    "if_true": {
                      "type": "minecraft:noise_threshold",
                      "max_threshold": 0.1818,
                      "min_threshold": -0.1818,
                      "noise": "minecraft:surface"
                    },
                    "then_run": {
                      "type": "minecraft:block",
                      "result_state": {
                        "Name": "minecraft:coarse_dirt"
                      }
                    }
                  },
                  {
                    "type": "minecraft:condition",
                    "if_true": {
                      "type": "minecraft:noise_threshold",
                      "max_threshold": 0.909,
                      "min_threshold": 0.5454,
                      "noise": "minecraft:surface"
                    },
                    "then_run": {
                      "type": "minecraft:block",
                      "result_state": {
                        "Name": "minecraft:coarse_dirt"
                      }
                    }
                  },
                  "minecraft:overworld/biome_surface/default"
                ]
              }
            }
          },
          {
            "type": "minecraft:condition",
            "if_true": {
              "type": "minecraft:biome",
              "biome_is": "minecraft:swamp"
            },
            "then_run": {
              "type": "minecraft:condition",
              "if_true": {
                "type": "minecraft:y_above",
                "add_stone_depth": false,
                "anchor": {
                  "absolute": 62
                },
                "surface_depth_multiplier": 0
              },
              "then_run": {
                "type": "minecraft:condition",
                "if_true": {
                  "type": "minecraft:not",
                  "invert": {
                    "type": "minecraft:y_above",
                    "add_stone_depth": false,
                    "anchor": {
                      "absolute": 63
                    },
                    "surface_depth_multiplier": 0
                  }
                },
                "then_run": {
                  "type": "minecraft:condition",
                  "if_true": {
                    "type": "minecraft:noise_threshold",
                    "max_threshold": 1.7976931348623157E308,
                    "min_threshold": 0.0,
                    "noise": "minecraft:surface_swamp"
                  },
                  "then_run": {
                    "type": "minecraft:block",
                    "result_state": {
                      "Name": "minecraft:water",
                      "Properties": {
                        "level": "0"
                      }
                    }
                  }
                }
              }
            }
          },
          {
            "type": "minecraft:condition",
            "if_true": {
              "type": "minecraft:biome",
              "biome_is": "minecraft:mangrove_swamp"
            },
            "then_run": {
              "type": "minecraft:condition",
              "if_true": {
                "type": "minecraft:y_above",
                "add_stone_depth": false,
                "anchor": {
                  "absolute": 60
                },
                "surface_depth_multiplier": 0
              },
              "then_run": {
                "type": "minecraft:condition",
                "if_true": {
                  "type": "minecraft:not",
                  "invert": {
                    "type": "minecraft:y_above",
                    "add_stone_depth": false,
                    "anchor": {
                      "absolute": 63
                    },
                    "surface_depth_multiplier": 0
                  }
                },
                "then_run": {
                  "type": "minecraft:condition",
                  "if_true": {
                    "type": "minecraft:noise_threshold",
                    "max_threshold": 1.7976931348623157E308,
                    "min_threshold": 0.0,
                    "noise": "minecraft:surface_swamp"
                  },
                  "then_run": {
                    "type": "minecraft:block",
                    "result_state": {
                      "Name": "minecraft:water",
                      "Properties": {
                        "level": "0"
                      }
                    }
                  }
                }
              }
            }
          }
        ]
      }
    },
    {
      "type": "minecraft:condition",
      "if_true": {
        "type": "minecraft:biome",
        "biome_is": [
          "minecraft:badlands",
          "minecraft:eroded_badlands",
          "minecraft:wooded_badlands"
        ]
      },
      "then_run": {
        "type": "minecraft:sequence",
        "sequence": [
          {
            "type": "minecraft:condition",
            "if_true": "minecraft:on_floor",
            "then_run": {
              "type": "minecraft:sequence",
              "sequence": [
                {
                  "type": "minecraft:condition",
                  "if_true": {
                    "type": "minecraft:y_above",
                    "add_stone_depth": false,
                    "anchor": {
                      "absolute": 256
                    },
                    "surface_depth_multiplier": 0
                  },
                  "then_run": {
                    "type": "minecraft:block",
                    "result_state": {
                      "Name": "minecraft:orange_terracotta"
                    }
                  }
                },
                {
                  "type": "minecraft:condition",
                  "if_true": {
                    "type": "minecraft:y_above",
                    "add_stone_depth": true,
                    "anchor": {
                      "absolute": 74
                    },
                    "surface_depth_multiplier": 1
                  },
                  "then_run": {
                    "type": "minecraft:sequence",
                    "sequence": [
                      {
                        "type": "minecraft:condition",
                        "if_true": {
                          "type": "minecraft:noise_threshold",
                          "max_threshold": -0.5454,
                          "min_threshold": -0.909,
                          "noise": "minecraft:surface"
                        },
                        "then_run": {
                          "type": "minecraft:block",
                          "result_state": {
                            "Name": "minecraft:terracotta"
                          }
                        }
                      },
                      {
                        "type": "minecraft:condition",
                        "if_true": {
                          "type": "minecraft:noise_threshold",
                          "max_threshold": 0.1818,
                          "min_threshold": -0.1818,
                          "noise": "minecraft:surface"
                        },
                        "then_run": {
                          "type": "minecraft:block",
                          "result_state": {
                            "Name": "minecraft:terracotta"
                          }
                        }
                      },
                      {
                        "type": "minecraft:condition",
                        "if_true": {
                          "type": "minecraft:noise_threshold",
                          "max_threshold": 0.909,
                          "min_threshold": 0.5454,
                          "noise": "minecraft:surface"
                        },
                        "then_run": {
                          "type": "minecraft:block",
                          "result_state": {
                            "Name": "minecraft:terracotta"
                          }
                        }
                      },
                      {
                        "type": "minecraft:bandlands"
                      }
                    ]
                  }
                },
                {
                  "type": "minecraft:condition",
                  "if_true": "minecraft:not_underwater",
                  "then_run": {
                    "type": "minecraft:sequence",
                    "sequence": [
                      {
                        "type": "minecraft:condition",
                        "if_true": "minecraft:on_ceiling",
                        "then_run": {
                          "type": "minecraft:block",
                          "result_state": {
                            "Name": "minecraft:red_sandstone"
                          }
                        }
                      },
                      {
                        "type": "minecraft:block",
                        "result_state": {
                          "Name": "minecraft:red_sand"
                        }
                      }
                    ]
                  }
                },
                {
                  "type": "minecraft:condition",
                  "if_true": {
                    "type": "minecraft:not",
                    "invert": {
                      "type": "minecraft:hole"
                    }
                  },
                  "then_run": {
                    "type": "minecraft:block",
                    "result_state": {
                      "Name": "minecraft:orange_terracotta"
                    }
                  }
                },
                {
                  "type": "minecraft:condition",
                  "if_true": "minecraft:not_under_deep_water",
                  "then_run": {
                    "type": "minecraft:block",
                    "result_state": {
                      "Name": "minecraft:white_terracotta"
                    }
                  }
                },
                "minecraft:overworld/gravel_or_stone_if_ceiling"
              ]
            }
          },
          {
            "type": "minecraft:condition",
            "if_true": {
              "type": "minecraft:y_above",
              "add_stone_depth": true,
              "anchor": {
                "absolute": 63
              },
              "surface_depth_multiplier": -1
            },
            "then_run": {
              "type": "minecraft:sequence",
              "sequence": [
                {
                  "type": "minecraft:condition",
                  "if_true": {
                    "type": "minecraft:y_above",
                    "add_stone_depth": false,
                    "anchor": {
                      "absolute": 63
                    },
                    "surface_depth_multiplier": 0
                  },
                  "then_run": {
                    "type": "minecraft:condition",
                    "if_true": {
                      "type": "minecraft:not",
                      "invert": {
                        "type": "minecraft:y_above",
                        "add_stone_depth": true,
                        "anchor": {
                          "absolute": 74
                        },
                        "surface_depth_multiplier": 1
                      }
                    },
                    "then_run": {
                      "type": "minecraft:block",
                      "result_state": {
                        "Name": "minecraft:orange_terracotta"
                      }
                    }
                  }
                },
                {
                  "type": "minecraft:bandlands"
                }
              ]
            }
          },
          {
            "type": "minecraft:condition",
            "if_true": "minecraft:under_floor",
            "then_run": {
              "type": "minecraft:condition",
              "if_true": "minecraft:not_under_deep_water",
              "then_run": {
                "type": "minecraft:block",
                "result_state": {
                  "Name": "minecraft:white_terracotta"
                }
              }
            }
          }
        ]
      }
    },
    {
      "type": "minecraft:condition",
      "if_true": "minecraft:on_floor",
      "then_run": {
        "type": "minecraft:condition",
        "if_true": "minecraft:not_underwater",
        "then_run": {
          "type": "minecraft:sequence",
          "sequence": [
            {
              "type": "minecraft:condition",
              "if_true": {
                "type": "minecraft:biome",
                "biome_is": [
                  "minecraft:frozen_ocean",
                  "minecraft:deep_frozen_ocean"
                ]
              },
              "then_run": {
                "type": "minecraft:condition",
                "if_true": {
                  "type": "minecraft:hole"
                },
                "then_run": {
                  "type": "minecraft:sequence",
                  "sequence": [
                    {
                      "type": "minecraft:condition",
                      "if_true": "minecraft:above_water",
                      "then_run": {
                        "type": "minecraft:block",
                        "result_state": {
                          "Name": "minecraft:air"
                        }
                      }
                    },
                    {
                      "type": "minecraft:condition",
                      "if_true": {
                        "type": "minecraft:temperature"
                      },
                      "then_run": {
                        "type": "minecraft:block",
                        "result_state": {
                          "Name": "minecraft:ice"
                        }
                      }
                    },
                    {
                      "type": "minecraft:block",
                      "result_state": {
                        "Name": "minecraft:water",
                        "Properties": {
                          "level": "0"
                        }
                      }
                    }
                  ]
                }
              }
            },
            "minecraft:overworld/biome_surface"
          ]
        }
      }
    },
    {
      "type": "minecraft:condition",
      "if_true": "minecraft:not_under_deep_water",
      "then_run": {
        "type": "minecraft:sequence",
        "sequence": [
          {
            "type": "minecraft:condition",
            "if_true": "minecraft:on_floor",
            "then_run": {
              "type": "minecraft:condition",
              "if_true": {
                "type": "minecraft:biome",
                "biome_is": [
                  "minecraft:frozen_ocean",
                  "minecraft:deep_frozen_ocean"
                ]
              },
              "then_run": {
                "type": "minecraft:condition",
                "if_true": {
                  "type": "minecraft:hole"
                },
                "then_run": {
                  "type": "minecraft:block",
                  "result_state": {
                    "Name": "minecraft:water",
                    "Properties": {
                      "level": "0"
                    }
                  }
                }
              }
            }
          },
          {
            "type": "minecraft:condition",
            "if_true": "minecraft:under_floor",
            "then_run": "minecraft:overworld/under_biome_surface"
          },
          {
            "type": "minecraft:condition",
            "if_true": {
              "type": "minecraft:biome",
              "biome_is": [
                "minecraft:warm_ocean",
                "minecraft:beach",
                "minecraft:snowy_beach"
              ]
            },
            "then_run": {
              "type": "minecraft:condition",
              "if_true": "minecraft:deep_under_floor",
              "then_run": {
                "type": "minecraft:block",
                "result_state": {
                  "Name": "minecraft:sandstone"
                }
              }
            }
          },
          {
            "type": "minecraft:condition",
            "if_true": {
              "type": "minecraft:biome",
              "biome_is": "minecraft:desert"
            },
            "then_run": {
              "type": "minecraft:condition",
              "if_true": "minecraft:very_deep_under_floor",
              "then_run": {
                "type": "minecraft:block",
                "result_state": {
                  "Name": "minecraft:sandstone"
                }
              }
            }
          }
        ]
      }
    },
    {
      "type": "minecraft:condition",
      "if_true": "minecraft:on_floor",
      "then_run": {
        "type": "minecraft:sequence",
        "sequence": [
          {
            "type": "minecraft:condition",
            "if_true": {
              "type": "minecraft:biome",
              "biome_is": [
                "minecraft:frozen_peaks",
                "minecraft:jagged_peaks"
              ]
            },
            "then_run": {
              "type": "minecraft:block",
              "result_state": {
                "Name": "minecraft:stone"
              }
            }
          },
          {
            "type": "minecraft:condition",
            "if_true": {
              "type": "minecraft:biome",
              "biome_is": [
                "minecraft:warm_ocean",
                "minecraft:lukewarm_ocean",
                "minecraft:deep_lukewarm_ocean"
              ]
            },
            "then_run": "minecraft:overworld/sand_or_sandstone_if_ceiling"
          },
          "minecraft:overworld/gravel_or_stone_if_ceiling"
        ]
      }
    }
  ]
}